flask_openapi4/.DS_Store
flask_openapi4/__init__.py
flask_openapi4/__version__.py
flask_openapi4/blueprint.py
flask_openapi4/commands.py
flask_openapi4/models/__init__.py
flask_openapi4/models/callback.py
flask_openapi4/models/components.py
flask_openapi4/models/contact.py
flask_openapi4/models/data_type.py
flask_openapi4/models/discriminator.py
flask_openapi4/models/encoding.py
flask_openapi4/models/example.py
flask_openapi4/models/external_documentation.py
flask_openapi4/models/file.py
flask_openapi4/models/header.py
flask_openapi4/models/info.py
flask_openapi4/models/license.py
flask_openapi4/models/link.py
flask_openapi4/models/media_type.py
flask_openapi4/models/oauth_flow.py
flask_openapi4/models/oauth_flows.py
flask_openapi4/models/operation.py
flask_openapi4/models/parameter.py
flask_openapi4/models/parameter_in_type.py
flask_openapi4/models/path_item.py
flask_openapi4/models/paths.py
flask_openapi4/models/reference.py
flask_openapi4/models/request_body.py
flask_openapi4/models/response.py
flask_openapi4/models/responses.py
flask_openapi4/models/schema.py
flask_openapi4/models/security_requirement.py
flask_openapi4/models/security_scheme.py
flask_openapi4/models/security_scheme_in_type.py
flask_openapi4/models/server.py
flask_openapi4/models/server_variable.py
flask_openapi4/models/style_values.py
flask_openapi4/models/tag.py
flask_openapi4/models/validation_error.py
flask_openapi4/models/xml.py
flask_openapi4/openapi.py
flask_openapi4/plugins.py
flask_openapi4/py.typed
flask_openapi4/request.py
flask_openapi4/scaffold.py
flask_openapi4/templates.py
flask_openapi4/types.py
flask_openapi4/utils.py
flask_openapi4/view.py
flask_openapi4-0.1.3.dist-info/LICENSE.rst
flask_openapi4-0.1.3.dist-info/METADATA
flask_openapi4-0.1.3.dist-info/WHEEL
flask_openapi4-0.1.3.dist-info/RECORD
